newline/__init__.py
newline/newline.py
newline/newline1.py
newline-0.1.0.dist-info/METADATA
newline-0.1.0.dist-info/WHEEL
newline-0.1.0.dist-info/top_level.txt
newline-0.1.0.dist-info/RECORD
