Metadata-Version: 2.1
Name: newline
Version: 0.1.0
Summary: A small package to make it easy to store data in CSV format using python
Home-page: https://github.com/Ayush-sharma-py/NewLine.git
Author: Ayush Sharma
Author-email: ayushsharma14@gmail.com
Classifier: Programming Language :: Python :: 3
Classifier: License :: OSI Approved :: MIT License
Classifier: Operating System :: OS Independent
Requires-Python: >=3.6
